tapioca_mandrill
