Metadata-Version: 1.1
Name: tapioca-mandrill
Version: 0.2.1
Summary: Mandrill API wrappper using Tapioca
Home-page: https://github.com/vintasoftware/tapioca-mandrill
Author: Filipe Ximenes
Author-email: filipeximenes@gmail.com
License: BSD
Keywords: mandrill,tapioca,wrapper,api
Platform: UNKNOWN
Classifier: Development Status :: 2 - Pre-Alpha
Classifier: Intended Audience :: Developers
Classifier: License :: OSI Approved :: BSD License
Classifier: Natural Language :: English
Classifier: Programming Language :: Python :: 2
Classifier: Programming Language :: Python :: 2.7
